{
    "windows" : {
        "vmname" : "bittly-windows-10-x64",
        "address" : "192.168.0.160",
        "port" : 5985,
        "user" : "bittly",
        "password" : "bittly",
        "workpath" : "C:\\Users\\bittly\\Desktop\\bittly"
    },
    "ubuntu" : {
        "vmname" : "bittly-ubuntu-22.04.1-x64",
        "address" : "192.168.0.161",
        "user" : "bittly",
        "workpath" : "/home/bittly/bittly"
    },
    "server" : {
        "dbAddress" : "/* address to server database address */",
        "dbUser" : "/* user name to server database address */",
        "dbPasswd" : "/* passwrod to server database address */",
        "dbName" : "/* name of database */"
    }
}